replacefs/__init__.py
replacefs/__main__.py
replacefs/colors.py
replacefs/log.py
replacefs/replacefs.py
replacefs-1.2.0.dist-info/LICENSE
replacefs-1.2.0.dist-info/METADATA
replacefs-1.2.0.dist-info/WHEEL
replacefs-1.2.0.dist-info/entry_points.txt
replacefs-1.2.0.dist-info/top_level.txt
replacefs-1.2.0.dist-info/RECORD
