Metadata-Version: 2.1
Name: replacefs
Version: 1.2.0
Summary: Search and replace CLI tool for strings on the all system
Home-page: https://github.com/yoarch/replace
Author: yoarch
Author-email: yo.managements@gmail.com
License: UNKNOWN
Platform: UNKNOWN
Classifier: Programming Language :: Python :: 3
Classifier: License :: OSI Approved :: MIT License
Classifier: Operating System :: OS Independent
Requires-Python: >=3
